iqsylani46214/init.py
iqsylani46214-0.1.dist-info/METADATA
iqsylani46214-0.1.dist-info/WHEEL
iqsylani46214-0.1.dist-info/license.txt
iqsylani46214-0.1.dist-info/top_level.txt
iqsylani46214-0.1.dist-info/RECORD
