Metadata-Version: 2.1
Name: iqsylani46214
Version: 0.1
Summary: this is a package created by iqbal
Author: Iqbal Ahmed
License: UNKNOWN
Platform: UNKNOWN
License-File: license.txt
